{
  "classes": {
    "6eb421db-bfbd-4c93-95ec-a1ee1a681ecd": {
      "id": "6eb421db-bfbd-4c93-95ec-a1ee1a681ecd",
      "name": "数学竞赛班",
      "description": "AMC 8 数学竞赛准备班级",
      "created_date": "2025-09-26",
      "students": {
        "5966505c-dc79-4985-8056-27f469d1cd52": {
          "id": "5966505c-dc79-4985-8056-27f469d1cd52",
          "name": "小明",
          "avatar_color": "linear-gradient(135deg, #667eea 0%, #764ba2 100%)",
          "total_score_all_courses": 0,
          "courses_attended": [],
          "attendance_rate": 100,
          "absence_count": 0,
          "long_term_member": true,
          "created_date": "2025-09-26"
        },
        "f7c207b8-723d-4cb2-b830-e007825ec1b6": {
          "id": "f7c207b8-723d-4cb2-b830-e007825ec1b6",
          "name": "小红",
          "avatar_color": "linear-gradient(135deg, #f093fb 0%, #f5576c 100%)",
          "total_score_all_courses": 0,
          "courses_attended": [],
          "attendance_rate": 100,
          "absence_count": 0,
          "long_term_member": true,
          "created_date": "2025-09-26"
        },
        "1b890d0e-a0a5-496f-83e2-bd64ad81e882": {
          "id": "1b890d0e-a0a5-496f-83e2-bd64ad81e882",
          "name": "1",
          "avatar_color": "linear-gradient(135deg, #4facfe 0%, #00f2fe 100%)",
          "total_score_all_courses": 0,
          "courses_attended": [],
          "attendance_rate": 100,
          "absence_count": 0,
          "long_term_member": true,
          "created_date": "2025-09-26"
        }
      },
      "courses": [
        {
          "id": "3b7cb807-1e6a-4a17-9804-3384d1f3e2a5",
          "name": "123",
          "class_id": "6eb421db-bfbd-4c93-95ec-a1ee1a681ecd",
          "start_date": "2025-09-26",
          "end_date": null,
          "is_active": false,
          "current_round": 3,
          "round_active": false,
          "start_time": 1758911677.937729,
          "current_answers": {},
          "answer_times": {},
          "correct_answer": "",
          "round_results": [
            {
              "round": 1,
              "correct_answer": "7",
              "question_score": 1,
              "results": {
                "5966505c-dc79-4985-8056-27f469d1cd52": {
                  "answer": "7",
                  "correct": true,
                  "score": 1
                },
                "f7c207b8-723d-4cb2-b830-e007825ec1b6": {
                  "answer": "4",
                  "correct": false,
                  "score": 0
                }
              }
            },
            {
              "round": 1,
              "correct_answer": "1",
              "question_score": 1,
              "results": {
                "5966505c-dc79-4985-8056-27f469d1cd52": {
                  "answer": "1",
                  "correct": true,
                  "score": 2
                },
                "f7c207b8-723d-4cb2-b830-e007825ec1b6": {
                  "answer": "1",
                  "correct": true,
                  "score": 1
                }
              }
            },
            {
              "round": 2,
              "correct_answer": "1",
              "question_score": 1,
              "results": {
                "5966505c-dc79-4985-8056-27f469d1cd52": {
                  "answer": "1",
                  "correct": true,
                  "score": 3
                },
                "f7c207b8-723d-4cb2-b830-e007825ec1b6": {
                  "answer": "2",
                  "correct": false,
                  "score": 1
                }
              }
            },
            {
              "round": 2,
              "correct_answer": "1",
              "question_score": 1,
              "results": {
                "5966505c-dc79-4985-8056-27f469d1cd52": {
                  "answer": "1",
                  "correct": true,
                  "score": 4
                },
                "f7c207b8-723d-4cb2-b830-e007825ec1b6": {
                  "answer": "2",
                  "correct": false,
                  "score": 1
                }
              }
            },
            {
              "round": 2,
              "correct_answer": "1",
              "question_score": 1,
              "results": {
                "5966505c-dc79-4985-8056-27f469d1cd52": {
                  "answer": "1",
                  "correct": true,
                  "score": 5
                },
                "f7c207b8-723d-4cb2-b830-e007825ec1b6": {
                  "answer": "2",
                  "correct": false,
                  "score": 1
                }
              }
            }
          ],
          "submissions": [],
          "students": {
            "5966505c-dc79-4985-8056-27f469d1cd52": {
              "student_id": "5966505c-dc79-4985-8056-27f469d1cd52",
              "name": "小明",
              "avatar_color": "linear-gradient(135deg, #667eea 0%, #764ba2 100%)",
              "course_id": "3b7cb807-1e6a-4a17-9804-3384d1f3e2a5",
              "score": 5,
              "total_rounds": 5,
              "correct_rounds": 5,
              "expression": "neutral",
              "animation": "none",
              "last_answer": "",
              "last_answer_time": 1.9075191020965576,
              "answers": []
            },
            "f7c207b8-723d-4cb2-b830-e007825ec1b6": {
              "student_id": "f7c207b8-723d-4cb2-b830-e007825ec1b6",
              "name": "小红",
              "avatar_color": "linear-gradient(135deg, #f093fb 0%, #f5576c 100%)",
              "course_id": "3b7cb807-1e6a-4a17-9804-3384d1f3e2a5",
              "score": 1,
              "total_rounds": 5,
              "correct_rounds": 1,
              "expression": "neutral",
              "animation": "none",
              "last_answer": "",
              "last_answer_time": 2.5718138217926025,
              "answers": []
            }
          },
          "status": "completed",
          "end_time": 1759040776.2426112
        },
        {
          "id": "5278754d-8821-4919-9e69-0de64d507995",
          "name": "divisor",
          "class_id": "6eb421db-bfbd-4c93-95ec-a1ee1a681ecd",
          "start_date": "2025-09-26",
          "end_date": null,
          "is_active": true,
          "current_round": 1,
          "round_active": false,
          "start_time": null,
          "current_answers": {},
          "answer_times": {},
          "correct_answer": "",
          "round_results": [],
          "submissions": [],
          "students": {
            "5966505c-dc79-4985-8056-27f469d1cd52": {
              "student_id": "5966505c-dc79-4985-8056-27f469d1cd52",
              "name": "小明",
              "avatar_color": "linear-gradient(135deg, #667eea 0%, #764ba2 100%)",
              "course_id": "5278754d-8821-4919-9e69-0de64d507995",
              "score": 0,
              "total_rounds": 0,
              "correct_rounds": 0,
              "expression": "neutral",
              "animation": "none",
              "last_answer": "",
              "last_answer_time": 0,
              "answers": []
            },
            "f7c207b8-723d-4cb2-b830-e007825ec1b6": {
              "student_id": "f7c207b8-723d-4cb2-b830-e007825ec1b6",
              "name": "小红",
              "avatar_color": "linear-gradient(135deg, #f093fb 0%, #f5576c 100%)",
              "course_id": "5278754d-8821-4919-9e69-0de64d507995",
              "score": 0,
              "total_rounds": 0,
              "correct_rounds": 0,
              "expression": "neutral",
              "animation": "none",
              "last_answer": "",
              "last_answer_time": 0,
              "answers": []
            },
            "1b890d0e-a0a5-496f-83e2-bd64ad81e882": {
              "student_id": "1b890d0e-a0a5-496f-83e2-bd64ad81e882",
              "name": "1",
              "avatar_color": "linear-gradient(135deg, #4facfe 0%, #00f2fe 100%)",
              "course_id": "5278754d-8821-4919-9e69-0de64d507995",
              "score": 0,
              "total_rounds": 0,
              "correct_rounds": 0,
              "expression": "neutral",
              "animation": "none",
              "last_answer": "",
              "last_answer_time": 0,
              "answers": []
            }
          }
        },
        {
          "id": "5804d470-53fc-460b-93ac-f475123bd7f5",
          "name": "123123",
          "class_id": "6eb421db-bfbd-4c93-95ec-a1ee1a681ecd",
          "start_date": "2025-09-26",
          "end_date": null,
          "is_active": true,
          "current_round": 1,
          "round_active": false,
          "start_time": null,
          "current_answers": {},
          "answer_times": {},
          "correct_answer": "",
          "round_results": [],
          "submissions": [],
          "students": {}
        },
        {
          "id": "b1345e7e-c32b-455c-9fd9-f14f44ab2698",
          "name": "11111111",
          "class_id": "6eb421db-bfbd-4c93-95ec-a1ee1a681ecd",
          "start_date": "2025-09-26",
          "end_date": null,
          "is_active": true,
          "current_round": 2,
          "round_active": true,
          "start_time": 1758945451.7874777,
          "current_answers": {},
          "answer_times": {},
          "correct_answer": "",
          "round_results": [
            {
              "round": 1,
              "correct_answer": "1",
              "question_score": 1,
              "results": {
                "5966505c-dc79-4985-8056-27f469d1cd52": {
                  "answer": "2",
                  "correct": false,
                  "score": 0
                },
                "f7c207b8-723d-4cb2-b830-e007825ec1b6": {
                  "answer": "1",
                  "correct": true,
                  "score": 1
                },
                "1b890d0e-a0a5-496f-83e2-bd64ad81e882": {
                  "answer": "1",
                  "correct": true,
                  "score": 1
                }
              }
            }
          ],
          "submissions": [],
          "students": {
            "5966505c-dc79-4985-8056-27f469d1cd52": {
              "student_id": "5966505c-dc79-4985-8056-27f469d1cd52",
              "name": "小明",
              "avatar_color": "linear-gradient(135deg, #667eea 0%, #764ba2 100%)",
              "course_id": "b1345e7e-c32b-455c-9fd9-f14f44ab2698",
              "score": 0,
              "total_rounds": 1,
              "correct_rounds": 0,
              "expression": "neutral",
              "animation": "none",
              "last_answer": "",
              "last_answer_time": 2.607590436935425,
              "answers": []
            },
            "f7c207b8-723d-4cb2-b830-e007825ec1b6": {
              "student_id": "f7c207b8-723d-4cb2-b830-e007825ec1b6",
              "name": "小红",
              "avatar_color": "linear-gradient(135deg, #f093fb 0%, #f5576c 100%)",
              "course_id": "b1345e7e-c32b-455c-9fd9-f14f44ab2698",
              "score": 1,
              "total_rounds": 1,
              "correct_rounds": 1,
              "expression": "neutral",
              "animation": "none",
              "last_answer": "",
              "last_answer_time": 3.4469974040985107,
              "answers": []
            },
            "1b890d0e-a0a5-496f-83e2-bd64ad81e882": {
              "student_id": "1b890d0e-a0a5-496f-83e2-bd64ad81e882",
              "name": "1",
              "avatar_color": "linear-gradient(135deg, #4facfe 0%, #00f2fe 100%)",
              "course_id": "b1345e7e-c32b-455c-9fd9-f14f44ab2698",
              "score": 1,
              "total_rounds": 1,
              "correct_rounds": 1,
              "expression": "neutral",
              "animation": "none",
              "last_answer": "",
              "last_answer_time": 1.9587273597717285,
              "answers": []
            }
          }
        },
        {
          "id": "1ef93d66-3656-41c8-81df-36065d61bae5",
          "name": "22222",
          "class_id": "6eb421db-bfbd-4c93-95ec-a1ee1a681ecd",
          "start_date": "2025-09-26",
          "end_date": null,
          "is_active": true,
          "current_round": 1,
          "round_active": false,
          "start_time": null,
          "current_answers": {},
          "answer_times": {},
          "correct_answer": "",
          "round_results": [],
          "submissions": [],
          "students": {
            "5966505c-dc79-4985-8056-27f469d1cd52": {
              "student_id": "5966505c-dc79-4985-8056-27f469d1cd52",
              "name": "小明",
              "avatar_color": "linear-gradient(135deg, #667eea 0%, #764ba2 100%)",
              "course_id": "1ef93d66-3656-41c8-81df-36065d61bae5",
              "score": 0,
              "total_rounds": 0,
              "correct_rounds": 0,
              "expression": "neutral",
              "animation": "none",
              "last_answer": "",
              "last_answer_time": 0,
              "answers": []
            },
            "f7c207b8-723d-4cb2-b830-e007825ec1b6": {
              "student_id": "f7c207b8-723d-4cb2-b830-e007825ec1b6",
              "name": "小红",
              "avatar_color": "linear-gradient(135deg, #f093fb 0%, #f5576c 100%)",
              "course_id": "1ef93d66-3656-41c8-81df-36065d61bae5",
              "score": 0,
              "total_rounds": 0,
              "correct_rounds": 0,
              "expression": "neutral",
              "animation": "none",
              "last_answer": "",
              "last_answer_time": 0,
              "answers": []
            },
            "1b890d0e-a0a5-496f-83e2-bd64ad81e882": {
              "student_id": "1b890d0e-a0a5-496f-83e2-bd64ad81e882",
              "name": "1",
              "avatar_color": "linear-gradient(135deg, #4facfe 0%, #00f2fe 100%)",
              "course_id": "1ef93d66-3656-41c8-81df-36065d61bae5",
              "score": 0,
              "total_rounds": 0,
              "correct_rounds": 0,
              "expression": "neutral",
              "animation": "none",
              "last_answer": "",
              "last_answer_time": 0,
              "answers": []
            }
          }
        },
        {
          "id": "ea5b27d2-b4c8-4c9a-aa9a-de839a16dab3",
          "name": "33333",
          "class_id": "6eb421db-bfbd-4c93-95ec-a1ee1a681ecd",
          "start_date": "2025-09-26",
          "end_date": null,
          "is_active": true,
          "current_round": 1,
          "round_active": false,
          "start_time": null,
          "current_answers": {},
          "answer_times": {},
          "correct_answer": "",
          "round_results": [],
          "submissions": [],
          "students": {}
        },
        {
          "id": "fc47a187-9a95-41ef-b0c8-7cc5bc5c8ac4",
          "name": "amc10",
          "class_id": "6eb421db-bfbd-4c93-95ec-a1ee1a681ecd",
          "start_date": "2025-09-26",
          "end_date": null,
          "is_active": true,
          "current_round": 1,
          "round_active": false,
          "start_time": null,
          "current_answers": {},
          "answer_times": {},
          "correct_answer": "",
          "round_results": [],
          "submissions": [],
          "students": {}
        },
        {
          "id": "f5fe50cb-6f68-4016-9c59-49fb11351c41",
          "name": "44444",
          "class_id": "6eb421db-bfbd-4c93-95ec-a1ee1a681ecd",
          "start_date": "2025-09-26",
          "end_date": null,
          "is_active": true,
          "current_round": 1,
          "round_active": false,
          "start_time": null,
          "current_answers": {},
          "answer_times": {},
          "correct_answer": "",
          "round_results": [],
          "submissions": [],
          "students": {}
        },
        {
          "id": "a83b85b5-f6ab-4014-ad4f-98ba37883827",
          "name": "123123123",
          "class_id": "6eb421db-bfbd-4c93-95ec-a1ee1a681ecd",
          "start_date": "2025-09-26",
          "end_date": null,
          "is_active": true,
          "current_round": 1,
          "round_active": false,
          "start_time": null,
          "current_answers": {},
          "answer_times": {},
          "correct_answer": "",
          "round_results": [],
          "submissions": [],
          "students": {}
        },
        {
          "id": "39a5ec73-a245-4bcb-a125-4e4b31eae354",
          "name": "111123123123",
          "class_id": "6eb421db-bfbd-4c93-95ec-a1ee1a681ecd",
          "start_date": "2025-09-26",
          "end_date": null,
          "is_active": true,
          "current_round": 1,
          "round_active": false,
          "start_time": null,
          "current_answers": {},
          "answer_times": {},
          "correct_answer": "",
          "round_results": [],
          "submissions": [],
          "students": {}
        },
        {
          "id": "2461f715-492d-4da0-8b50-6d54dd97a84a",
          "name": "2222",
          "class_id": "6eb421db-bfbd-4c93-95ec-a1ee1a681ecd",
          "start_date": "2025-09-26",
          "end_date": null,
          "is_active": false,
          "current_round": 2,
          "round_active": false,
          "start_time": 1758951035.201875,
          "current_answers": {},
          "answer_times": {},
          "correct_answer": "",
          "round_results": [
            {
              "round": 1,
              "correct_answer": "2",
              "question_score": 1,
              "results": {
                "5966505c-dc79-4985-8056-27f469d1cd52": {
                  "answer": "1",
                  "correct": false,
                  "score": 0
                },
                "f7c207b8-723d-4cb2-b830-e007825ec1b6": {
                  "answer": "3",
                  "correct": false,
                  "score": 0
                },
                "1b890d0e-a0a5-496f-83e2-bd64ad81e882": {
                  "answer": "2",
                  "correct": true,
                  "score": 1
                }
              }
            }
          ],
          "submissions": [],
          "students": {
            "5966505c-dc79-4985-8056-27f469d1cd52": {
              "student_id": "5966505c-dc79-4985-8056-27f469d1cd52",
              "name": "小明",
              "avatar_color": "linear-gradient(135deg, #667eea 0%, #764ba2 100%)",
              "course_id": "2461f715-492d-4da0-8b50-6d54dd97a84a",
              "score": 0,
              "total_rounds": 1,
              "correct_rounds": 0,
              "expression": "neutral",
              "animation": "none",
              "last_answer": "",
              "last_answer_time": 4.7600672245025635,
              "answers": []
            },
            "f7c207b8-723d-4cb2-b830-e007825ec1b6": {
              "student_id": "f7c207b8-723d-4cb2-b830-e007825ec1b6",
              "name": "小红",
              "avatar_color": "linear-gradient(135deg, #f093fb 0%, #f5576c 100%)",
              "course_id": "2461f715-492d-4da0-8b50-6d54dd97a84a",
              "score": 0,
              "total_rounds": 1,
              "correct_rounds": 0,
              "expression": "neutral",
              "animation": "none",
              "last_answer": "",
              "last_answer_time": 5.78644061088562,
              "answers": []
            },
            "1b890d0e-a0a5-496f-83e2-bd64ad81e882": {
              "student_id": "1b890d0e-a0a5-496f-83e2-bd64ad81e882",
              "name": "1",
              "avatar_color": "linear-gradient(135deg, #4facfe 0%, #00f2fe 100%)",
              "course_id": "2461f715-492d-4da0-8b50-6d54dd97a84a",
              "score": 1,
              "total_rounds": 1,
              "correct_rounds": 1,
              "expression": "neutral",
              "animation": "none",
              "last_answer": "",
              "last_answer_time": 3.942168712615967,
              "answers": []
            }
          },
          "status": "completed",
          "end_time": 1758951053.4535894
        }
      ],
      "active_course": "2461f715-492d-4da0-8b50-6d54dd97a84a",
      "competition_goal_id": "c9a0686a-606a-4ac1-9792-351774c8dd8f",
      "is_active": false,
      "ended_date": "2025-10-01"
    },
    "3a3dffd7-0a98-45e7-a5f4-34cde8efe361": {
      "id": "3a3dffd7-0a98-45e7-a5f4-34cde8efe361",
      "name": "123",
      "description": "1",
      "created_date": "2025-09-26",
      "competition_goal_id": "c9a0686a-606a-4ac1-9792-351774c8dd8f",
      "students": {
        "fa3e8d98-3bd5-4b67-bdb6-467e59f8113c": {
          "id": "fa3e8d98-3bd5-4b67-bdb6-467e59f8113c",
          "name": "",
          "avatar_color": "linear-gradient(135deg, #4facfe 0%, #00f2fe 100%)",
          "total_score_all_courses": 0,
          "courses_attended": [],
          "attendance_rate": 100,
          "absence_count": 0,
          "long_term_member": true,
          "created_date": "2025-09-26"
        },
        "7778dcd0-4481-456a-8640-da61acf1bd0b": {
          "id": "7778dcd0-4481-456a-8640-da61acf1bd0b",
          "name": "",
          "avatar_color": "linear-gradient(135deg, #4facfe 0%, #00f2fe 100%)",
          "total_score_all_courses": 0,
          "courses_attended": [],
          "attendance_rate": 100,
          "absence_count": 0,
          "long_term_member": true,
          "created_date": "2025-09-26"
        }
      },
      "courses": [
        {
          "id": "39bfe583-fe37-4700-8460-e43dca81ab93",
          "name": "1111",
          "class_id": "3a3dffd7-0a98-45e7-a5f4-34cde8efe361",
          "start_date": "2025-09-26",
          "end_date": null,
          "is_active": true,
          "current_round": 2,
          "round_active": false,
          "start_time": 1758949907.8825173,
          "current_answers": {},
          "answer_times": {},
          "correct_answer": "",
          "round_results": [
            {
              "round": 1,
              "correct_answer": "1",
              "question_score": 1,
              "results": {
                "fa3e8d98-3bd5-4b67-bdb6-467e59f8113c": {
                  "answer": "",
                  "correct": false,
                  "score": 0
                },
                "7778dcd0-4481-456a-8640-da61acf1bd0b": {
                  "answer": "",
                  "correct": false,
                  "score": 0
                },
                "bf288a91-9626-4053-ac21-15bd64400044": {
                  "answer": "1",
                  "correct": true,
                  "score": 1
                },
                "63ebf14f-cfa3-4d15-83e3-1be0c2224b89": {
                  "answer": "2",
                  "correct": false,
                  "score": 0
                }
              }
            }
          ],
          "submissions": [],
          "students": {
            "fa3e8d98-3bd5-4b67-bdb6-467e59f8113c": {
              "student_id": "fa3e8d98-3bd5-4b67-bdb6-467e59f8113c",
              "name": "",
              "avatar_color": "linear-gradient(135deg, #4facfe 0%, #00f2fe 100%)",
              "course_id": "39bfe583-fe37-4700-8460-e43dca81ab93",
              "score": 0,
              "total_rounds": 1,
              "correct_rounds": 0,
              "expression": "neutral",
              "animation": "none",
              "last_answer": "",
              "last_answer_time": 0,
              "answers": []
            },
            "7778dcd0-4481-456a-8640-da61acf1bd0b": {
              "student_id": "7778dcd0-4481-456a-8640-da61acf1bd0b",
              "name": "",
              "avatar_color": "linear-gradient(135deg, #4facfe 0%, #00f2fe 100%)",
              "course_id": "39bfe583-fe37-4700-8460-e43dca81ab93",
              "score": 0,
              "total_rounds": 1,
              "correct_rounds": 0,
              "expression": "neutral",
              "animation": "none",
              "last_answer": "",
              "last_answer_time": 0,
              "answers": []
            },
            "bf288a91-9626-4053-ac21-15bd64400044": {
              "student_id": "bf288a91-9626-4053-ac21-15bd64400044",
              "name": "2222",
              "avatar_color": "linear-gradient(135deg, #ffecd2 0%, #fcb69f 100%)",
              "score": 1,
              "total_rounds": 1,
              "correct_rounds": 1,
              "expression": "neutral",
              "animation": "none",
              "last_answer": "",
              "last_answer_time": 5.181023836135864,
              "answers": []
            },
            "63ebf14f-cfa3-4d15-83e3-1be0c2224b89": {
              "student_id": "63ebf14f-cfa3-4d15-83e3-1be0c2224b89",
              "name": "11",
              "avatar_color": "linear-gradient(135deg, #ff9a9e 0%, #fecfef 100%)",
              "score": 0,
              "total_rounds": 1,
              "correct_rounds": 0,
              "expression": "neutral",
              "animation": "none",
              "last_answer": "",
              "last_answer_time": 4.387520790100098,
              "answers": []
            }
          }
        }
      ],
      "active_course": "39bfe583-fe37-4700-8460-e43dca81ab93",
      "is_active": false,
      "ended_date": "2025-10-01"
    },
    "0b63662a-97cf-4667-ae3a-dc959d53675a": {
      "id": "0b63662a-97cf-4667-ae3a-dc959d53675a",
      "name": "B12竞赛班",
      "description": "周六上午10-12",
      "created_date": "2025-09-27",
      "competition_goal_id": "c9a0686a-606a-4ac1-9792-351774c8dd8f",
      "students": {},
      "courses": [
        {
          "id": "e3348ad8-39e1-4ef9-9a6a-e1a09084515b",
          "name": "11",
          "class_id": "0b63662a-97cf-4667-ae3a-dc959d53675a",
          "start_date": "2025-09-27",
          "end_date": null,
          "is_active": false,
          "current_round": 5,
          "round_active": false,
          "start_time": 1759040041.2123673,
          "current_answers": {},
          "answer_times": {},
          "correct_answer": "",
          "round_results": [
            {
              "round": 1,
              "correct_answer": "1",
              "question_score": 1,
              "results": {
                "82fa5c51-c090-4aed-adae-ed74f3728f8e": {
                  "answer": "1",
                  "correct": true,
                  "score": 1
                },
                "05c3a057-ef89-4dce-bfe4-335d5f34555c": {
                  "answer": "1",
                  "correct": true,
                  "score": 1
                },
                "afa35c61-3964-4be7-868d-71e4b8247191": {
                  "answer": "1",
                  "correct": true,
                  "score": 1
                },
                "7e3f570b-00b4-4229-b094-2a2638ea1134": {
                  "answer": "2",
                  "correct": false,
                  "score": 0
                },
                "77fe41cc-9a6e-4ade-963b-e9a6beb30415": {
                  "answer": "",
                  "correct": false,
                  "score": 0
                }
              }
            },
            {
              "round": 2,
              "correct_answer": "2",
              "question_score": 1,
              "results": {
                "82fa5c51-c090-4aed-adae-ed74f3728f8e": {
                  "answer": "1",
                  "correct": false,
                  "score": 1
                },
                "05c3a057-ef89-4dce-bfe4-335d5f34555c": {
                  "answer": "2",
                  "correct": true,
                  "score": 2
                },
                "afa35c61-3964-4be7-868d-71e4b8247191": {
                  "answer": "2",
                  "correct": true,
                  "score": 2
                },
                "7e3f570b-00b4-4229-b094-2a2638ea1134": {
                  "answer": "",
                  "correct": false,
                  "score": 0
                },
                "77fe41cc-9a6e-4ade-963b-e9a6beb30415": {
                  "answer": "",
                  "correct": false,
                  "score": 0
                }
              }
            },
            {
              "round": 3,
              "correct_answer": "5",
              "question_score": 5,
              "results": {
                "82fa5c51-c090-4aed-adae-ed74f3728f8e": {
                  "answer": "5",
                  "correct": true,
                  "score": 6
                },
                "05c3a057-ef89-4dce-bfe4-335d5f34555c": {
                  "answer": "5",
                  "correct": true,
                  "score": 7
                },
                "afa35c61-3964-4be7-868d-71e4b8247191": {
                  "answer": "",
                  "correct": false,
                  "score": 2
                },
                "7e3f570b-00b4-4229-b094-2a2638ea1134": {
                  "answer": "",
                  "correct": false,
                  "score": 0
                },
                "77fe41cc-9a6e-4ade-963b-e9a6beb30415": {
                  "answer": "",
                  "correct": false,
                  "score": 0
                }
              }
            },
            {
              "round": 4,
              "correct_answer": "1",
              "question_score": 1,
              "results": {
                "82fa5c51-c090-4aed-adae-ed74f3728f8e": {
                  "answer": "1",
                  "correct": true,
                  "score": 7
                },
                "05c3a057-ef89-4dce-bfe4-335d5f34555c": {
                  "answer": "1",
                  "correct": true,
                  "score": 8
                },
                "afa35c61-3964-4be7-868d-71e4b8247191": {
                  "answer": "2",
                  "correct": false,
                  "score": 2
                },
                "7e3f570b-00b4-4229-b094-2a2638ea1134": {
                  "answer": "",
                  "correct": false,
                  "score": 0
                },
                "77fe41cc-9a6e-4ade-963b-e9a6beb30415": {
                  "answer": "",
                  "correct": false,
                  "score": 0
                }
              }
            }
          ],
          "submissions": [],
          "students": {
            "82fa5c51-c090-4aed-adae-ed74f3728f8e": {
              "student_id": "82fa5c51-c090-4aed-adae-ed74f3728f8e",
              "name": "11",
              "avatar_color": "linear-gradient(135deg, #f093fb 0%, #f5576c 100%)",
              "course_id": "e3348ad8-39e1-4ef9-9a6a-e1a09084515b",
              "score": 7,
              "total_rounds": 4,
              "correct_rounds": 3,
              "expression": "neutral",
              "animation": "none",
              "last_answer": "",
              "last_answer_time": 1.88576340675354,
              "answers": []
            },
            "05c3a057-ef89-4dce-bfe4-335d5f34555c": {
              "student_id": "05c3a057-ef89-4dce-bfe4-335d5f34555c",
              "name": "22",
              "avatar_color": "linear-gradient(135deg, #4facfe 0%, #00f2fe 100%)",
              "course_id": "e3348ad8-39e1-4ef9-9a6a-e1a09084515b",
              "score": 8,
              "total_rounds": 4,
              "correct_rounds": 4,
              "expression": "neutral",
              "animation": "none",
              "last_answer": "",
              "last_answer_time": 3.087947130203247,
              "answers": []
            },
            "afa35c61-3964-4be7-868d-71e4b8247191": {
              "student_id": "afa35c61-3964-4be7-868d-71e4b8247191",
              "name": "33",
              "avatar_color": "linear-gradient(135deg, #ffecd2 0%, #fcb69f 100%)",
              "course_id": "e3348ad8-39e1-4ef9-9a6a-e1a09084515b",
              "score": 2,
              "total_rounds": 4,
              "correct_rounds": 2,
              "expression": "neutral",
              "animation": "none",
              "last_answer": "",
              "last_answer_time": 4.20613169670105,
              "answers": []
            },
            "7e3f570b-00b4-4229-b094-2a2638ea1134": {
              "student_id": "7e3f570b-00b4-4229-b094-2a2638ea1134",
              "name": "44",
              "avatar_color": "linear-gradient(135deg, #4facfe 0%, #00f2fe 100%)",
              "course_id": "e3348ad8-39e1-4ef9-9a6a-e1a09084515b",
              "score": 0,
              "total_rounds": 3,
              "correct_rounds": 0,
              "expression": "neutral",
              "animation": "none",
              "last_answer": "",
              "last_answer_time": 5.143318176269531,
              "answers": []
            },
            "77fe41cc-9a6e-4ade-963b-e9a6beb30415": {
              "student_id": "77fe41cc-9a6e-4ade-963b-e9a6beb30415",
              "name": "55",
              "avatar_color": "linear-gradient(135deg, #a8edea 0%, #fed6e3 100%)",
              "course_id": "e3348ad8-39e1-4ef9-9a6a-e1a09084515b",
              "score": 0,
              "total_rounds": 3,
              "correct_rounds": 0,
              "expression": "neutral",
              "animation": "none",
              "last_answer": "",
              "last_answer_time": 0,
              "answers": []
            }
          },
          "status": "completed",
          "end_time": 1759040064.7507234
        },
        {
          "id": "f3baadf5-3c96-47e4-9a37-cc6c03134c72",
          "name": "123",
          "start_date": "2025-09-27T23:53:58.668568",
          "is_active": true
        },
        {
          "id": "9fd7cc80-8e07-42fe-b441-f5597134ee92",
          "name": "123",
          "start_date": "2025-09-27T23:55:08.076176",
          "is_active": true
        },
        {
          "id": "ddf9a1d6-6b6c-4182-8ecf-a9dd372792df",
          "name": "1234",
          "start_date": "2025-09-27T23:56:04.885205",
          "is_active": true
        },
        {
          "id": "24b95569-10e1-485d-aca1-bc8c9dbef69c",
          "name": "2223334",
          "start_date": "2025-09-27T23:56:53.599093",
          "is_active": true
        },
        {
          "id": "8e218371-ffcd-4049-b8b3-9dbb12ab72ea",
          "name": "555",
          "start_date": "2025-10-01T15:39:17.719813",
          "is_active": true
        }
      ],
      "active_course": "e3348ad8-39e1-4ef9-9a6a-e1a09084515b",
      "is_active": false,
      "ended_date": "2025-10-01"
    },
    "368d7e52-8b84-41e9-b5dc-7fad38eced10": {
      "id": "368d7e52-8b84-41e9-b5dc-7fad38eced10",
      "name": "1",
      "description": "1",
      "students": {
        "dce90a34-7312-40fd-9c76-532ea9d06e6b": {
          "id": "dce90a34-7312-40fd-9c76-532ea9d06e6b",
          "name": "11",
          "class_id": "368d7e52-8b84-41e9-b5dc-7fad38eced10",
          "created_date": "2025-10-03"
        },
        "a68c8fab-593f-4999-947d-46cc49b8898a": {
          "id": "a68c8fab-593f-4999-947d-46cc49b8898a",
          "name": "12",
          "class_id": "368d7e52-8b84-41e9-b5dc-7fad38eced10",
          "created_date": "2025-10-03"
        },
        "153527b9-34e5-43e0-a816-798398e1f29c": {
          "id": "153527b9-34e5-43e0-a816-798398e1f29c",
          "name": "13",
          "class_id": "368d7e52-8b84-41e9-b5dc-7fad38eced10",
          "created_date": "2025-10-03"
        }
      },
      "courses": [],
      "competition_goal_id": null,
      "is_active": false,
      "created_date": "2025-10-03",
      "ended_date": "2025-10-08"
    },
    "6016fecd-ce97-4856-b957-4cae109416c5": {
      "id": "6016fecd-ce97-4856-b957-4cae109416c5",
      "name": "VISST竞赛班",
      "description": "周四中午13:10-14:40",
      "students": {
        "d6f7cf32-9c55-4661-9e48-03740b17ec5f": {
          "id": "d6f7cf32-9c55-4661-9e48-03740b17ec5f",
          "name": "1",
          "class_id": "6016fecd-ce97-4856-b957-4cae109416c5",
          "created_date": "2025-10-08",
          "avatar_color": "linear-gradient(135deg, #6b8253 0%, #6febb5 100%)",
          "total_score_all_courses": 0,
          "courses_attended": [],
          "attendance_rate": 100,
          "absence_count": 0,
          "long_term_member": true
        },
        "a4747145-eed3-4bf1-8880-90bcb26d796e": {
          "id": "a4747145-eed3-4bf1-8880-90bcb26d796e",
          "name": "2",
          "class_id": "6016fecd-ce97-4856-b957-4cae109416c5",
          "created_date": "2025-10-08",
          "avatar_color": "linear-gradient(135deg, #b76fcd 0%, #2d7891 100%)",
          "total_score_all_courses": 0,
          "courses_attended": [],
          "attendance_rate": 100,
          "absence_count": 0,
          "long_term_member": true
        }
      },
      "courses": [
        {
          "id": "2974516d-fbd6-4361-ad63-e845417ef3e0",
          "name": "数学课堂测试",
          "start_date": "2025-10-08",
          "current_round": 1,
          "is_active": true
        },
        {
          "id": "8f35b1f2-246f-41be-9b17-6678dafc74b4",
          "name": "",
          "start_date": "2025-10-08",
          "current_round": 1,
          "is_active": true
        },
        {
          "id": "36da9822-fed2-422a-be96-c221fc242597",
          "name": "",
          "start_date": "2025-10-08",
          "current_round": 2,
          "is_active": true
        },
        {
          "id": "3888b1ed-a940-4e66-8909-442602da4059",
          "name": "",
          "start_date": "2025-10-08",
          "current_round": 2,
          "is_active": true
        }
      ],
      "competition_goal_id": "ad6432f4-c1f4-4cbf-a97c-90219d9dd902",
      "is_active": true,
      "created_date": "2025-10-08"
    }
  },
  "competition_goals": {
    "8f278a41-aa1c-46f1-a826-ff75b1e568e9": {
      "id": "8f278a41-aa1c-46f1-a826-ff75b1e568e9",
      "name": "AMC 8 竞赛",
      "description": "美国数学竞赛 AMC 8 准备",
      "goal_date": "2025-01-15",
      "created_date": "2025-09-26",
      "is_active": false,
      "ended_date": "2025-10-08"
    },
    "c9a0686a-606a-4ac1-9792-351774c8dd8f": {
      "id": "c9a0686a-606a-4ac1-9792-351774c8dd8f",
      "name": "amc10",
      "description": "111",
      "goal_date": "2025-12-18",
      "created_date": "2025-09-26",
      "is_active": false,
      "ended_date": "2025-10-08"
    },
    "ad6432f4-c1f4-4cbf-a97c-90219d9dd902": {
      "id": "ad6432f4-c1f4-4cbf-a97c-90219d9dd902",
      "name": "AMC 10",
      "description": "1111",
      "goal_date": "2025-11-05",
      "is_active": true,
      "ended_date": null,
      "created_date": "2025-10-08"
    }
  },
  "courses": {
    "3b7cb807-1e6a-4a17-9804-3384d1f3e2a5": {
      "id": "3b7cb807-1e6a-4a17-9804-3384d1f3e2a5",
      "students": {
        "小明": {
          "name": "小明",
          "score": 5,
          "total_rounds": 5,
          "correct_rounds": 5,
          "last_answer_time": 1.9075191020965576,
          "expression": "neutral",
          "animation": "none",
          "avatar_color": "linear-gradient(135deg, #667eea 0%, #764ba2 100%)",
          "answers": [],
          "last_answer": ""
        },
        "小红": {
          "name": "小红",
          "score": 1,
          "total_rounds": 5,
          "correct_rounds": 1,
          "last_answer_time": 2.5718138217926025,
          "expression": "neutral",
          "animation": "none",
          "avatar_color": "linear-gradient(135deg, #f093fb 0%, #f5576c 100%)",
          "answers": [],
          "last_answer": ""
        }
      },
      "submissions": [],
      "is_active": false,
      "start_time": 1758911677.937729,
      "current_round": 3,
      "round_active": false,
      "current_answers": {},
      "answer_times": {},
      "correct_answer": "",
      "round_results": [],
      "created_date": "2025-09-26"
    },
    "5278754d-8821-4919-9e69-0de64d507995": {
      "id": "5278754d-8821-4919-9e69-0de64d507995",
      "students": {
        "小明": {
          "name": "小明",
          "score": 0,
          "total_rounds": 0,
          "correct_rounds": 0,
          "last_answer_time": 0,
          "expression": "neutral",
          "animation": "none",
          "avatar_color": "linear-gradient(135deg, #667eea 0%, #764ba2 100%)",
          "answers": [],
          "last_answer": ""
        },
        "小红": {
          "name": "小红",
          "score": 0,
          "total_rounds": 0,
          "correct_rounds": 0,
          "last_answer_time": 0,
          "expression": "neutral",
          "animation": "none",
          "avatar_color": "linear-gradient(135deg, #f093fb 0%, #f5576c 100%)",
          "answers": [],
          "last_answer": ""
        },
        "1": {
          "name": "1",
          "score": 0,
          "total_rounds": 0,
          "correct_rounds": 0,
          "last_answer_time": 0,
          "expression": "neutral",
          "animation": "none",
          "avatar_color": "linear-gradient(135deg, #4facfe 0%, #00f2fe 100%)",
          "answers": [],
          "last_answer": ""
        }
      },
      "submissions": [],
      "is_active": true,
      "start_time": null,
      "current_round": 1,
      "round_active": false,
      "current_answers": {},
      "answer_times": {},
      "correct_answer": "",
      "round_results": [],
      "created_date": "2025-09-26"
    },
    "5804d470-53fc-460b-93ac-f475123bd7f5": {
      "id": "5804d470-53fc-460b-93ac-f475123bd7f5",
      "students": {},
      "submissions": [],
      "is_active": true,
      "start_time": null,
      "current_round": 1,
      "round_active": false,
      "current_answers": {},
      "answer_times": {},
      "correct_answer": "",
      "round_results": [],
      "created_date": "2025-09-26"
    },
    "b1345e7e-c32b-455c-9fd9-f14f44ab2698": {
      "id": "b1345e7e-c32b-455c-9fd9-f14f44ab2698",
      "students": {
        "小明": {
          "name": "小明",
          "score": 0,
          "total_rounds": 1,
          "correct_rounds": 0,
          "last_answer_time": 2.607590436935425,
          "expression": "neutral",
          "animation": "none",
          "avatar_color": "linear-gradient(135deg, #667eea 0%, #764ba2 100%)",
          "answers": [],
          "last_answer": ""
        },
        "小红": {
          "name": "小红",
          "score": 1,
          "total_rounds": 1,
          "correct_rounds": 1,
          "last_answer_time": 3.4469974040985107,
          "expression": "neutral",
          "animation": "none",
          "avatar_color": "linear-gradient(135deg, #f093fb 0%, #f5576c 100%)",
          "answers": [],
          "last_answer": ""
        },
        "1": {
          "name": "1",
          "score": 1,
          "total_rounds": 1,
          "correct_rounds": 1,
          "last_answer_time": 1.9587273597717285,
          "expression": "neutral",
          "animation": "none",
          "avatar_color": "linear-gradient(135deg, #4facfe 0%, #00f2fe 100%)",
          "answers": [],
          "last_answer": ""
        }
      },
      "submissions": [],
      "is_active": true,
      "start_time": 1758945451.7874777,
      "current_round": 2,
      "round_active": true,
      "current_answers": {},
      "answer_times": {},
      "correct_answer": "",
      "round_results": [],
      "created_date": "2025-09-26"
    },
    "1ef93d66-3656-41c8-81df-36065d61bae5": {
      "id": "1ef93d66-3656-41c8-81df-36065d61bae5",
      "students": {
        "小明": {
          "name": "小明",
          "score": 0,
          "total_rounds": 0,
          "correct_rounds": 0,
          "last_answer_time": 0,
          "expression": "neutral",
          "animation": "none",
          "avatar_color": "linear-gradient(135deg, #667eea 0%, #764ba2 100%)",
          "answers": [],
          "last_answer": ""
        },
        "小红": {
          "name": "小红",
          "score": 0,
          "total_rounds": 0,
          "correct_rounds": 0,
          "last_answer_time": 0,
          "expression": "neutral",
          "animation": "none",
          "avatar_color": "linear-gradient(135deg, #f093fb 0%, #f5576c 100%)",
          "answers": [],
          "last_answer": ""
        },
        "1": {
          "name": "1",
          "score": 0,
          "total_rounds": 0,
          "correct_rounds": 0,
          "last_answer_time": 0,
          "expression": "neutral",
          "animation": "none",
          "avatar_color": "linear-gradient(135deg, #4facfe 0%, #00f2fe 100%)",
          "answers": [],
          "last_answer": ""
        }
      },
      "submissions": [],
      "is_active": true,
      "start_time": null,
      "current_round": 1,
      "round_active": false,
      "current_answers": {},
      "answer_times": {},
      "correct_answer": "",
      "round_results": [],
      "created_date": "2025-09-26"
    },
    "ea5b27d2-b4c8-4c9a-aa9a-de839a16dab3": {
      "id": "ea5b27d2-b4c8-4c9a-aa9a-de839a16dab3",
      "students": {},
      "submissions": [],
      "is_active": true,
      "start_time": null,
      "current_round": 1,
      "round_active": false,
      "current_answers": {},
      "answer_times": {},
      "correct_answer": "",
      "round_results": [],
      "created_date": "2025-09-26"
    },
    "fc47a187-9a95-41ef-b0c8-7cc5bc5c8ac4": {
      "id": "fc47a187-9a95-41ef-b0c8-7cc5bc5c8ac4",
      "students": {},
      "submissions": [],
      "is_active": true,
      "start_time": null,
      "current_round": 1,
      "round_active": false,
      "current_answers": {},
      "answer_times": {},
      "correct_answer": "",
      "round_results": [],
      "created_date": "2025-09-26"
    },
    "f5fe50cb-6f68-4016-9c59-49fb11351c41": {
      "id": "f5fe50cb-6f68-4016-9c59-49fb11351c41",
      "students": {},
      "submissions": [],
      "is_active": true,
      "start_time": null,
      "current_round": 1,
      "round_active": false,
      "current_answers": {},
      "answer_times": {},
      "correct_answer": "",
      "round_results": [],
      "created_date": "2025-09-26"
    },
    "a83b85b5-f6ab-4014-ad4f-98ba37883827": {
      "id": "a83b85b5-f6ab-4014-ad4f-98ba37883827",
      "students": {},
      "submissions": [],
      "is_active": true,
      "start_time": null,
      "current_round": 1,
      "round_active": false,
      "current_answers": {},
      "answer_times": {},
      "correct_answer": "",
      "round_results": [],
      "created_date": "2025-09-26"
    },
    "39a5ec73-a245-4bcb-a125-4e4b31eae354": {
      "id": "39a5ec73-a245-4bcb-a125-4e4b31eae354",
      "students": {},
      "submissions": [],
      "is_active": true,
      "start_time": null,
      "current_round": 1,
      "round_active": false,
      "current_answers": {},
      "answer_times": {},
      "correct_answer": "",
      "round_results": [],
      "created_date": "2025-09-26"
    },
    "2461f715-492d-4da0-8b50-6d54dd97a84a": {
      "id": "2461f715-492d-4da0-8b50-6d54dd97a84a",
      "students": {
        "小明": {
          "name": "小明",
          "score": 0,
          "total_rounds": 1,
          "correct_rounds": 0,
          "last_answer_time": 4.7600672245025635,
          "expression": "neutral",
          "animation": "none",
          "avatar_color": "linear-gradient(135deg, #667eea 0%, #764ba2 100%)",
          "answers": [],
          "last_answer": ""
        },
        "小红": {
          "name": "小红",
          "score": 0,
          "total_rounds": 1,
          "correct_rounds": 0,
          "last_answer_time": 5.78644061088562,
          "expression": "neutral",
          "animation": "none",
          "avatar_color": "linear-gradient(135deg, #f093fb 0%, #f5576c 100%)",
          "answers": [],
          "last_answer": ""
        },
        "1": {
          "name": "1",
          "score": 1,
          "total_rounds": 1,
          "correct_rounds": 1,
          "last_answer_time": 3.942168712615967,
          "expression": "neutral",
          "animation": "none",
          "avatar_color": "linear-gradient(135deg, #4facfe 0%, #00f2fe 100%)",
          "answers": [],
          "last_answer": ""
        }
      },
      "submissions": [],
      "is_active": false,
      "start_time": 1758951035.201875,
      "current_round": 2,
      "round_active": false,
      "current_answers": {},
      "answer_times": {},
      "correct_answer": "",
      "round_results": [],
      "created_date": "2025-09-26"
    },
    "39bfe583-fe37-4700-8460-e43dca81ab93": {
      "id": "39bfe583-fe37-4700-8460-e43dca81ab93",
      "students": {
        "": {
          "name": "",
          "score": 0,
          "total_rounds": 1,
          "correct_rounds": 0,
          "last_answer_time": 0,
          "expression": "neutral",
          "animation": "none",
          "avatar_color": "linear-gradient(135deg, #4facfe 0%, #00f2fe 100%)",
          "answers": [],
          "last_answer": ""
        },
        "2222": {
          "name": "2222",
          "score": 1,
          "total_rounds": 1,
          "correct_rounds": 1,
          "last_answer_time": 5.181023836135864,
          "expression": "neutral",
          "animation": "none",
          "avatar_color": "linear-gradient(135deg, #ffecd2 0%, #fcb69f 100%)",
          "answers": [],
          "last_answer": ""
        }
      },
      "submissions": [],
      "is_active": true,
      "start_time": 1758949907.8825173,
      "current_round": 2,
      "round_active": false,
      "current_answers": {},
      "answer_times": {},
      "correct_answer": "",
      "round_results": [],
      "created_date": "2025-09-26"
    },
    "e3348ad8-39e1-4ef9-9a6a-e1a09084515b": {
      "id": "e3348ad8-39e1-4ef9-9a6a-e1a09084515b",
      "students": {},
      "submissions": [],
      "is_active": false,
      "start_time": 1759040041.2123673,
      "current_round": 5,
      "round_active": false,
      "current_answers": {},
      "answer_times": {},
      "correct_answer": "",
      "round_results": [],
      "created_date": "2025-09-27"
    },
    "f3baadf5-3c96-47e4-9a37-cc6c03134c72": {
      "id": "f3baadf5-3c96-47e4-9a37-cc6c03134c72",
      "name": "123",
      "class_id": "0b63662a-97cf-4667-ae3a-dc959d53675a",
      "students": {},
      "submissions": [],
      "is_active": false,
      "start_time": "2025-09-27T23:53:58.668568",
      "current_round": 1,
      "round_active": false,
      "current_answers": {},
      "answer_times": {},
      "correct_answer": "",
      "round_results": [],
      "created_date": "2025-09-27T23:53:58.668568"
    },
    "9fd7cc80-8e07-42fe-b441-f5597134ee92": {
      "id": "9fd7cc80-8e07-42fe-b441-f5597134ee92",
      "name": "123",
      "class_id": "0b63662a-97cf-4667-ae3a-dc959d53675a",
      "students": {},
      "submissions": [],
      "is_active": false,
      "start_time": "2025-09-27T23:55:08.076176",
      "current_round": 1,
      "round_active": false,
      "current_answers": {},
      "answer_times": {},
      "correct_answer": "",
      "round_results": [],
      "created_date": "2025-09-27T23:55:08.076176"
    },
    "ddf9a1d6-6b6c-4182-8ecf-a9dd372792df": {
      "id": "ddf9a1d6-6b6c-4182-8ecf-a9dd372792df",
      "name": "1234",
      "class_id": "0b63662a-97cf-4667-ae3a-dc959d53675a",
      "students": {},
      "submissions": [],
      "is_active": false,
      "start_time": "2025-09-27T23:56:04.885205",
      "current_round": 1,
      "round_active": false,
      "current_answers": {},
      "answer_times": {},
      "correct_answer": "",
      "round_results": [],
      "created_date": "2025-09-27T23:56:04.885205"
    },
    "24b95569-10e1-485d-aca1-bc8c9dbef69c": {
      "id": "24b95569-10e1-485d-aca1-bc8c9dbef69c",
      "name": "2223334",
      "class_id": "0b63662a-97cf-4667-ae3a-dc959d53675a",
      "students": {},
      "submissions": [],
      "is_active": false,
      "start_time": 1759043245.4250996,
      "current_round": 2,
      "round_active": true,
      "current_answers": {},
      "answer_times": {},
      "correct_answer": "",
      "round_results": [
        {
          "round": 1,
          "correct_answer": "1",
          "question_score": 1,
          "results": {
            "11": {
              "answer": "1",
              "correct": true,
              "score": 1,
              "answer_time": 0
            },
            "22": {
              "answer": "2",
              "correct": false,
              "score": 0,
              "answer_time": 0
            },
            "33": {
              "answer": "1",
              "correct": true,
              "score": 1,
              "answer_time": 0
            },
            "44": {
              "answer": "2",
              "correct": false,
              "score": 0,
              "answer_time": 0
            },
            "55": {
              "answer": "",
              "correct": false,
              "score": 0,
              "answer_time": 0
            }
          }
        },
        {
          "round": 1,
          "correct_answer": "1",
          "question_score": 1,
          "results": {
            "11": {
              "answer": "1",
              "correct": true,
              "score": 2,
              "answer_time": 0
            },
            "22": {
              "answer": "1",
              "correct": true,
              "score": 1,
              "answer_time": 0
            },
            "33": {
              "answer": "2",
              "correct": false,
              "score": 1,
              "answer_time": 0
            },
            "44": {
              "answer": "",
              "correct": false,
              "score": 0,
              "answer_time": 0
            },
            "55": {
              "answer": "",
              "correct": false,
              "score": 0,
              "answer_time": 0
            }
          }
        },
        {
          "round": 1,
          "correct_answer": "1",
          "question_score": 1,
          "results": {
            "11": {
              "answer": "1",
              "correct": true,
              "score": 3,
              "answer_time": 0
            },
            "22": {
              "answer": "1",
              "correct": true,
              "score": 2,
              "answer_time": 0
            },
            "33": {
              "answer": "2",
              "correct": false,
              "score": 1,
              "answer_time": 0
            },
            "44": {
              "answer": "1",
              "correct": true,
              "score": 1,
              "answer_time": 0
            },
            "55": {
              "answer": "",
              "correct": false,
              "score": 0,
              "answer_time": 0
            }
          }
        },
        {
          "round": 1,
          "correct_answer": "1",
          "question_score": 1,
          "results": {
            "11": {
              "answer": "1",
              "correct": true,
              "score": 4,
              "answer_time": 0
            },
            "22": {
              "answer": "1",
              "correct": true,
              "score": 3,
              "answer_time": 0
            },
            "33": {
              "answer": "2",
              "correct": false,
              "score": 1,
              "answer_time": 0
            },
            "44": {
              "answer": "1",
              "correct": true,
              "score": 2,
              "answer_time": 0
            },
            "55": {
              "answer": "",
              "correct": false,
              "score": 0,
              "answer_time": 0
            }
          }
        },
        {
          "round": 1,
          "correct_answer": "1",
          "question_score": 3,
          "results": {
            "11": {
              "answer": "1",
              "correct": true,
              "score": 7,
              "answer_time": 0
            },
            "22": {
              "answer": "1",
              "correct": true,
              "score": 6,
              "answer_time": 0
            },
            "33": {
              "answer": "2",
              "correct": false,
              "score": 1,
              "answer_time": 0
            },
            "44": {
              "answer": "",
              "correct": false,
              "score": 2,
              "answer_time": 0
            },
            "55": {
              "answer": "",
              "correct": false,
              "score": 0,
              "answer_time": 0
            }
          }
        },
        {
          "round": 1,
          "correct_answer": "1",
          "question_score": 1,
          "results": {
            "11": {
              "answer": "",
              "correct": false,
              "score": 7,
              "answer_time": 0
            },
            "22": {
              "answer": "2",
              "correct": false,
              "score": 6,
              "answer_time": 0
            },
            "33": {
              "answer": "1",
              "correct": true,
              "score": 2,
              "answer_time": 0
            },
            "44": {
              "answer": "",
              "correct": false,
              "score": 2,
              "answer_time": 0
            },
            "55": {
              "answer": "",
              "correct": false,
              "score": 0,
              "answer_time": 0
            }
          }
        },
        {
          "round": 1,
          "correct_answer": "1",
          "question_score": 1,
          "results": {
            "11": {
              "answer": "1",
              "correct": true,
              "score": 8,
              "answer_time": 0
            },
            "22": {
              "answer": "1",
              "correct": true,
              "score": 7,
              "answer_time": 0
            },
            "33": {
              "answer": "2",
              "correct": false,
              "score": 2,
              "answer_time": 0
            },
            "44": {
              "answer": "",
              "correct": false,
              "score": 2,
              "answer_time": 0
            },
            "55": {
              "answer": "",
              "correct": false,
              "score": 0,
              "answer_time": 0
            }
          }
        },
        {
          "round": 1,
          "correct_answer": "1",
          "question_score": 3,
          "results": {
            "11": {
              "answer": "1",
              "correct": true,
              "score": 11,
              "answer_time": 0
            },
            "22": {
              "answer": "1",
              "correct": true,
              "score": 10,
              "answer_time": 0
            },
            "33": {
              "answer": "2",
              "correct": false,
              "score": 2,
              "answer_time": 0
            },
            "44": {
              "answer": "",
              "correct": false,
              "score": 2,
              "answer_time": 0
            },
            "55": {
              "answer": "",
              "correct": false,
              "score": 0,
              "answer_time": 0
            }
          }
        }
      ],
      "created_date": "2025-09-27T23:56:53.599093"
    },
    "8e218371-ffcd-4049-b8b3-9dbb12ab72ea": {
      "id": "8e218371-ffcd-4049-b8b3-9dbb12ab72ea",
      "name": "555",
      "class_id": "0b63662a-97cf-4667-ae3a-dc959d53675a",
      "students": {},
      "submissions": [],
      "is_active": false,
      "start_time": 1759363809.3560972,
      "current_round": 1,
      "round_active": false,
      "current_answers": {
        "22": "3",
        "11": "2"
      },
      "answer_times": {
        "22": 1759363812.5047665,
        "11": 1759363814.0634103
      },
      "correct_answer": "3",
      "round_results": [
        {
          "round": 1,
          "correct_answer": "2",
          "question_score": 3,
          "results": {
            "11": {
              "answer": "2",
              "correct": true,
              "score": 3,
              "answer_time": 4.707313060760498
            },
            "22": {
              "answer": "1",
              "correct": false,
              "score": 0,
              "answer_time": 3.1486692428588867
            },
            "33": {
              "answer": "2",
              "correct": true,
              "score": 3,
              "answer_time": 0
            },
            "44": {
              "answer": "",
              "correct": false,
              "score": 0,
              "answer_time": 0
            },
            "55": {
              "answer": "",
              "correct": false,
              "score": 0,
              "answer_time": 0
            }
          }
        },
        {
          "round": 1,
          "correct_answer": "1",
          "question_score": 1,
          "results": {
            "11": {
              "answer": "1",
              "correct": true,
              "score": 4,
              "answer_time": 4.707313060760498
            },
            "22": {
              "answer": "1",
              "correct": true,
              "score": 1,
              "answer_time": 3.1486692428588867
            },
            "33": {
              "answer": "1",
              "correct": true,
              "score": 4,
              "answer_time": 0
            },
            "44": {
              "answer": "2",
              "correct": false,
              "score": 0,
              "answer_time": 0
            },
            "55": {
              "answer": "",
              "correct": false,
              "score": 0,
              "answer_time": 0
            }
          }
        },
        {
          "round": 1,
          "correct_answer": "1",
          "question_score": 1,
          "results": {
            "11": {
              "answer": "1",
              "correct": true,
              "score": 5,
              "answer_time": 4.707313060760498
            },
            "22": {
              "answer": "1",
              "correct": true,
              "score": 2,
              "answer_time": 3.1486692428588867
            },
            "33": {
              "answer": "2",
              "correct": false,
              "score": 4,
              "answer_time": 0
            },
            "44": {
              "answer": "",
              "correct": false,
              "score": 0,
              "answer_time": 0
            },
            "55": {
              "answer": "",
              "correct": false,
              "score": 0,
              "answer_time": 0
            }
          }
        },
        {
          "round": 1,
          "correct_answer": "2",
          "question_score": 1,
          "results": {
            "11": {
              "answer": "2",
              "correct": true,
              "score": 6,
              "answer_time": 4.707313060760498
            },
            "22": {
              "answer": "1",
              "correct": false,
              "score": 2,
              "answer_time": 3.1486692428588867
            },
            "33": {
              "answer": "1",
              "correct": false,
              "score": 4,
              "answer_time": 0
            },
            "44": {
              "answer": "",
              "correct": false,
              "score": 0,
              "answer_time": 0
            },
            "55": {
              "answer": "",
              "correct": false,
              "score": 0,
              "answer_time": 0
            }
          }
        },
        {
          "round": 1,
          "correct_answer": "1",
          "question_score": 1,
          "results": {
            "11": {
              "answer": "1",
              "correct": true,
              "score": 7,
              "answer_time": 4.707313060760498
            },
            "22": {
              "answer": "1",
              "correct": true,
              "score": 3,
              "answer_time": 3.1486692428588867
            },
            "33": {
              "answer": "2",
              "correct": false,
              "score": 4,
              "answer_time": 0
            },
            "44": {
              "answer": "1",
              "correct": true,
              "score": 1,
              "answer_time": 0
            },
            "55": {
              "answer": "",
              "correct": false,
              "score": 0,
              "answer_time": 0
            }
          }
        },
        {
          "round": 1,
          "correct_answer": "1",
          "question_score": 1,
          "results": {
            "11": {
              "answer": "1",
              "correct": true,
              "score": 8,
              "answer_time": 4.707313060760498
            },
            "22": {
              "answer": "1",
              "correct": true,
              "score": 4,
              "answer_time": 3.1486692428588867
            },
            "33": {
              "answer": "1",
              "correct": true,
              "score": 5,
              "answer_time": 0
            },
            "44": {
              "answer": "2",
              "correct": false,
              "score": 1,
              "answer_time": 0
            },
            "55": {
              "answer": "",
              "correct": false,
              "score": 0,
              "answer_time": 0
            }
          }
        },
        {
          "round": 1,
          "correct_answer": "1",
          "question_score": 1,
          "results": {
            "11": {
              "answer": "1",
              "correct": true,
              "score": 9,
              "answer_time": 4.707313060760498
            },
            "22": {
              "answer": "1",
              "correct": true,
              "score": 5,
              "answer_time": 3.1486692428588867
            },
            "33": {
              "answer": "1",
              "correct": true,
              "score": 6,
              "answer_time": 0
            },
            "44": {
              "answer": "2",
              "correct": false,
              "score": 1,
              "answer_time": 0
            },
            "55": {
              "answer": "",
              "correct": false,
              "score": 0,
              "answer_time": 0
            }
          }
        },
        {
          "round": 1,
          "correct_answer": "1",
          "question_score": 1,
          "results": {
            "11": {
              "answer": "11",
              "correct": false,
              "score": 9,
              "answer_time": 4.707313060760498
            },
            "22": {
              "answer": "1",
              "correct": true,
              "score": 6,
              "answer_time": 3.1486692428588867
            },
            "33": {
              "answer": "2",
              "correct": false,
              "score": 6,
              "answer_time": 0
            },
            "44": {
              "answer": "1",
              "correct": true,
              "score": 2,
              "answer_time": 0
            },
            "55": {
              "answer": "",
              "correct": false,
              "score": 0,
              "answer_time": 0
            }
          }
        },
        {
          "round": 1,
          "correct_answer": "1",
          "question_score": 1,
          "results": {
            "11": {
              "answer": "1",
              "correct": true,
              "score": 10,
              "answer_time": 4.707313060760498
            },
            "22": {
              "answer": "1",
              "correct": true,
              "score": 7,
              "answer_time": 3.1486692428588867
            },
            "33": {
              "answer": "2",
              "correct": false,
              "score": 6,
              "answer_time": 0
            },
            "44": {
              "answer": "1",
              "correct": true,
              "score": 3,
              "answer_time": 0
            },
            "55": {
              "answer": "",
              "correct": false,
              "score": 0,
              "answer_time": 0
            }
          }
        },
        {
          "round": 1,
          "correct_answer": "2",
          "question_score": 1,
          "results": {
            "11": {
              "answer": "11",
              "correct": false,
              "score": 10,
              "answer_time": 4.707313060760498
            },
            "22": {
              "answer": "2",
              "correct": true,
              "score": 8,
              "answer_time": 3.1486692428588867
            },
            "33": {
              "answer": "2",
              "correct": true,
              "score": 7,
              "answer_time": 0
            },
            "44": {
              "answer": "2",
              "correct": true,
              "score": 4,
              "answer_time": 0
            },
            "55": {
              "answer": "",
              "correct": false,
              "score": 0,
              "answer_time": 0
            }
          }
        },
        {
          "round": 1,
          "correct_answer": "3",
          "question_score": 3,
          "results": {
            "11": {
              "answer": "2",
              "correct": false,
              "score": 10,
              "answer_time": 4.707313060760498
            },
            "22": {
              "answer": "3",
              "correct": true,
              "score": 11,
              "answer_time": 3.1486692428588867
            },
            "33": {
              "answer": "",
              "correct": false,
              "score": 7,
              "answer_time": 0
            },
            "44": {
              "answer": "",
              "correct": false,
              "score": 4,
              "answer_time": 0
            },
            "55": {
              "answer": "",
              "correct": false,
              "score": 0,
              "answer_time": 0
            }
          }
        }
      ],
      "created_date": "2025-10-01T15:39:17.719813"
    },
    "1e323e98-91bb-4dbb-96f4-b79842561fb4": {
      "id": "1e323e98-91bb-4dbb-96f4-b79842561fb4",
      "name": "",
      "class_id": "368d7e52-8b84-41e9-b5dc-7fad38eced10",
      "is_active": false,
      "created_date": "2025-10-03",
      "students": {},
      "submissions": [],
      "round_results": [],
      "current_round": 1,
      "round_active": false
    },
    "a45b9b6c-1847-4d27-9fc7-bd72a60c6c53": {
      "id": "a45b9b6c-1847-4d27-9fc7-bd72a60c6c53",
      "name": "",
      "class_id": "368d7e52-8b84-41e9-b5dc-7fad38eced10",
      "is_active": false,
      "created_date": "2025-10-03",
      "students": {},
      "submissions": [],
      "round_results": [],
      "current_round": 1,
      "round_active": false
    },
    "41cb610c-72c5-4e9f-b3c6-d0f18b9a7650": {
      "id": "41cb610c-72c5-4e9f-b3c6-d0f18b9a7650",
      "name": "",
      "class_id": "368d7e52-8b84-41e9-b5dc-7fad38eced10",
      "is_active": false,
      "created_date": "2025-10-03",
      "students": {},
      "submissions": [],
      "round_results": [],
      "current_round": 1,
      "round_active": false
    },
    "9d57de88-9dbb-4bcd-8573-827f503cac50": {
      "id": "9d57de88-9dbb-4bcd-8573-827f503cac50",
      "name": "",
      "class_id": "368d7e52-8b84-41e9-b5dc-7fad38eced10",
      "is_active": false,
      "created_date": "2025-10-03",
      "students": {},
      "submissions": [],
      "round_results": [],
      "current_round": 1,
      "round_active": false
    },
    "aaf9492e-22f1-45bc-945d-711ba0c9dff8": {
      "id": "aaf9492e-22f1-45bc-945d-711ba0c9dff8",
      "name": "",
      "class_id": "368d7e52-8b84-41e9-b5dc-7fad38eced10",
      "is_active": false,
      "created_date": "2025-10-08",
      "students": {
        "11": {
          "name": "11",
          "score": 2,
          "total_rounds": 2,
          "correct_rounds": 2,
          "last_answer_time": 0,
          "expression": "smile",
          "animation": "celebration",
          "avatar_color": "#4ecdc4",
          "answers": [],
          "last_answer": "2"
        },
        "12": {
          "name": "12",
          "score": 0,
          "total_rounds": 0,
          "correct_rounds": 0,
          "last_answer_time": 0,
          "expression": "embarrassed",
          "animation": "none",
          "avatar_color": "#4ecdc4",
          "answers": [],
          "last_answer": ""
        },
        "13": {
          "name": "13",
          "score": 0,
          "total_rounds": 0,
          "correct_rounds": 0,
          "last_answer_time": 0,
          "expression": "embarrassed",
          "animation": "none",
          "avatar_color": "#4ecdc4",
          "answers": [],
          "last_answer": ""
        }
      },
      "submissions": [],
      "round_results": [
        {
          "round": 1,
          "correct_answer": "1",
          "question_score": 1,
          "results": {
            "11": {
              "answer": "1",
              "correct": true,
              "score": 1,
              "answer_time": 1.8234193325042725
            },
            "12": {
              "answer": "",
              "correct": false,
              "score": 0,
              "answer_time": 0
            },
            "13": {
              "answer": "",
              "correct": false,
              "score": 0,
              "answer_time": 0
            }
          }
        },
        {
          "round": 1,
          "correct_answer": "2",
          "question_score": 1,
          "results": {
            "11": {
              "answer": "2",
              "correct": true,
              "score": 2,
              "answer_time": 1.8234193325042725
            },
            "12": {
              "answer": "",
              "correct": false,
              "score": 0,
              "answer_time": 0
            },
            "13": {
              "answer": "",
              "correct": false,
              "score": 0,
              "answer_time": 0
            }
          }
        }
      ],
      "current_round": 1,
      "round_active": false,
      "current_answers": {
        "11": "2"
      },
      "answer_times": {
        "11": 1759975603.1738305
      },
      "correct_answer": "2",
      "start_time": 1759975601.3504112
    },
    "b7db76ab-6a5a-4139-9e56-e033c22ac880": {
      "id": "b7db76ab-6a5a-4139-9e56-e033c22ac880",
      "name": "",
      "class_id": "368d7e52-8b84-41e9-b5dc-7fad38eced10",
      "is_active": false,
      "created_date": "2025-10-08",
      "students": {
        "11": {
          "name": "11",
          "score": 3,
          "total_rounds": 3,
          "correct_rounds": 3,
          "last_answer_time": 0,
          "expression": "smile",
          "animation": "celebration",
          "avatar_color": "#4ecdc4",
          "answers": [],
          "last_answer": "1"
        },
        "12": {
          "name": "12",
          "score": 0,
          "total_rounds": 1,
          "correct_rounds": 0,
          "last_answer_time": 0,
          "expression": "embarrassed",
          "animation": "none",
          "avatar_color": "#4ecdc4",
          "answers": [],
          "last_answer": ""
        },
        "13": {
          "name": "13",
          "score": 0,
          "total_rounds": 0,
          "correct_rounds": 0,
          "last_answer_time": 0,
          "expression": "embarrassed",
          "animation": "none",
          "avatar_color": "#4ecdc4",
          "answers": [],
          "last_answer": ""
        }
      },
      "submissions": [],
      "round_results": [
        {
          "round": 1,
          "correct_answer": "1",
          "question_score": 1,
          "results": {
            "11": {
              "answer": "1",
              "correct": true,
              "score": 1,
              "answer_time": 2.2906925678253174
            },
            "12": {
              "answer": "",
              "correct": false,
              "score": 0,
              "answer_time": 0
            },
            "13": {
              "answer": "",
              "correct": false,
              "score": 0,
              "answer_time": 0
            }
          }
        },
        {
          "round": 1,
          "correct_answer": "1",
          "question_score": 1,
          "results": {
            "11": {
              "answer": "1",
              "correct": true,
              "score": 2,
              "answer_time": 2.2906925678253174
            },
            "12": {
              "answer": "2",
              "correct": false,
              "score": 0,
              "answer_time": 0
            },
            "13": {
              "answer": "",
              "correct": false,
              "score": 0,
              "answer_time": 0
            }
          }
        },
        {
          "round": 1,
          "correct_answer": "1",
          "question_score": 1,
          "results": {
            "11": {
              "answer": "1",
              "correct": true,
              "score": 3,
              "answer_time": 2.2906925678253174
            },
            "12": {
              "answer": "",
              "correct": false,
              "score": 0,
              "answer_time": 0
            },
            "13": {
              "answer": "",
              "correct": false,
              "score": 0,
              "answer_time": 0
            }
          }
        }
      ],
      "current_round": 1,
      "round_active": false,
      "current_answers": {
        "11": "1"
      },
      "answer_times": {
        "11": 1759975864.9457705
      },
      "correct_answer": "1",
      "start_time": 1759975862.655078
    },
    "9313411e-7893-4ddd-868d-4bf9c1ad96e0": {
      "id": "9313411e-7893-4ddd-868d-4bf9c1ad96e0",
      "name": "",
      "class_id": "368d7e52-8b84-41e9-b5dc-7fad38eced10",
      "is_active": false,
      "created_date": "2025-10-08",
      "students": {
        "11": {
          "name": "11",
          "score": 8,
          "total_rounds": 5,
          "correct_rounds": 4,
          "last_answer_time": 0,
          "expression": "smile",
          "animation": "celebration",
          "avatar_color": "#4ecdc4",
          "answers": [],
          "last_answer": "1"
        },
        "12": {
          "name": "12",
          "score": 8,
          "total_rounds": 4,
          "correct_rounds": 4,
          "last_answer_time": 0,
          "expression": "smile",
          "animation": "celebration",
          "avatar_color": "#4ecdc4",
          "answers": [],
          "last_answer": "1"
        },
        "13": {
          "name": "13",
          "score": 0,
          "total_rounds": 0,
          "correct_rounds": 0,
          "last_answer_time": 0,
          "expression": "embarrassed",
          "animation": "none",
          "avatar_color": "#4ecdc4",
          "answers": [],
          "last_answer": ""
        }
      },
      "submissions": [],
      "round_results": [
        {
          "round": 1,
          "correct_answer": "1",
          "question_score": 1,
          "results": {
            "11": {
              "answer": "1",
              "correct": true,
              "score": 1,
              "answer_time": 1.2702627182006836
            },
            "12": {
              "answer": "",
              "correct": false,
              "score": 0,
              "answer_time": 1.8212618827819824
            },
            "13": {
              "answer": "",
              "correct": false,
              "score": 0,
              "answer_time": 0
            }
          }
        },
        {
          "round": 2,
          "correct_answer": "1",
          "question_score": 1,
          "results": {
            "11": {
              "answer": "11",
              "correct": false,
              "score": 1,
              "answer_time": 1.2702627182006836
            },
            "12": {
              "answer": "1",
              "correct": true,
              "score": 1,
              "answer_time": 1.8212618827819824
            },
            "13": {
              "answer": "",
              "correct": false,
              "score": 0,
              "answer_time": 0
            }
          }
        },
        {
          "round": 3,
          "correct_answer": "1",
          "question_score": 1,
          "results": {
            "11": {
              "answer": "1",
              "correct": true,
              "score": 2,
              "answer_time": 1.2702627182006836
            },
            "12": {
              "answer": "1",
              "correct": true,
              "score": 2,
              "answer_time": 1.8212618827819824
            },
            "13": {
              "answer": "",
              "correct": false,
              "score": 0,
              "answer_time": 0
            }
          }
        },
        {
          "round": 4,
          "correct_answer": "1",
          "question_score": 3,
          "results": {
            "11": {
              "answer": "1",
              "correct": true,
              "score": 5,
              "answer_time": 1.2702627182006836
            },
            "12": {
              "answer": "1",
              "correct": true,
              "score": 5,
              "answer_time": 1.8212618827819824
            },
            "13": {
              "answer": "",
              "correct": false,
              "score": 0,
              "answer_time": 0
            }
          }
        },
        {
          "round": 5,
          "correct_answer": "1",
          "question_score": 3,
          "results": {
            "11": {
              "answer": "1",
              "correct": true,
              "score": 8,
              "answer_time": 1.2702627182006836
            },
            "12": {
              "answer": "1",
              "correct": true,
              "score": 8,
              "answer_time": 1.8212618827819824
            },
            "13": {
              "answer": "",
              "correct": false,
              "score": 0,
              "answer_time": 0
            }
          }
        }
      ],
      "current_round": 5,
      "round_active": false,
      "current_answers": {
        "11": "1",
        "12": "1"
      },
      "answer_times": {
        "11": 1759976030.3705275,
        "12": 1759976030.9215267
      },
      "correct_answer": "1",
      "start_time": 1759976029.1002648
    },
    "2974516d-fbd6-4361-ad63-e845417ef3e0": {
      "id": "2974516d-fbd6-4361-ad63-e845417ef3e0",
      "name": "数学课堂测试",
      "class_id": "6016fecd-ce97-4856-b957-4cae109416c5",
      "is_active": true,
      "created_date": "2025-10-08",
      "students": {
        "1": {
          "name": "1",
          "score": 1,
          "total_rounds": 1,
          "correct_rounds": 1,
          "last_answer_time": 4.831409931182861,
          "expression": "smile",
          "animation": "celebration",
          "avatar_color": "linear-gradient(135deg, #6b8253 0%, #6febb5 100%)",
          "answers": [],
          "last_answer": "1"
        },
        "2": {
          "name": "2",
          "score": 0,
          "total_rounds": 1,
          "correct_rounds": 0,
          "last_answer_time": 10.036164283752441,
          "expression": "angry",
          "animation": "none",
          "avatar_color": "linear-gradient(135deg, #b76fcd 0%, #2d7891 100%)",
          "answers": [],
          "last_answer": "2"
        }
      },
      "submissions": [],
      "round_results": [
        {
          "round": 1,
          "correct_answer": "1",
          "question_score": 1,
          "results": {
            "1": {
              "answer": "1",
              "correct": true,
              "score": 1,
              "answer_time": 4.831409931182861
            },
            "2": {
              "answer": "2",
              "correct": false,
              "score": 0,
              "answer_time": 10.036164283752441
            }
          }
        }
      ],
      "current_round": 1,
      "round_active": false,
      "current_answers": {
        "1": "1",
        "2": "2"
      },
      "answer_times": {
        "1": 4.831409931182861,
        "2": 10.036164283752441
      },
      "correct_answer": "1",
      "start_time": 1759977351.3555937
    },
    "8f35b1f2-246f-41be-9b17-6678dafc74b4": {
      "id": "8f35b1f2-246f-41be-9b17-6678dafc74b4",
      "name": "",
      "class_id": "6016fecd-ce97-4856-b957-4cae109416c5",
      "is_active": true,
      "created_date": "2025-10-08",
      "students": {},
      "submissions": [],
      "round_results": [],
      "current_round": 1,
      "round_active": false
    },
    "36da9822-fed2-422a-be96-c221fc242597": {
      "id": "36da9822-fed2-422a-be96-c221fc242597",
      "name": "",
      "class_id": "6016fecd-ce97-4856-b957-4cae109416c5",
      "is_active": true,
      "created_date": "2025-10-08",
      "students": {
        "1": {
          "name": "1",
          "score": 3,
          "total_rounds": 2,
          "correct_rounds": 2,
          "last_answer_time": 7.9486329555511475,
          "expression": "smile",
          "animation": "celebration",
          "avatar_color": "linear-gradient(135deg, #6b8253 0%, #6febb5 100%)",
          "answers": [],
          "last_answer": "1"
        },
        "2": {
          "name": "2",
          "score": 1,
          "total_rounds": 2,
          "correct_rounds": 1,
          "last_answer_time": 11.035289287567139,
          "expression": "angry",
          "animation": "none",
          "avatar_color": "linear-gradient(135deg, #b76fcd 0%, #2d7891 100%)",
          "answers": [],
          "last_answer": "2"
        }
      },
      "submissions": [],
      "round_results": [
        {
          "round": 1,
          "correct_answer": "1",
          "question_score": 1,
          "results": {
            "1": {
              "answer": "1",
              "correct": true,
              "score": 1,
              "answer_time": 5.6885974407196045
            },
            "2": {
              "answer": "1",
              "correct": true,
              "score": 1,
              "answer_time": 12.361505031585693
            }
          }
        },
        {
          "round": 2,
          "correct_answer": "1",
          "question_score": 2,
          "results": {
            "1": {
              "answer": "1",
              "correct": true,
              "score": 3,
              "answer_time": 7.9486329555511475
            },
            "2": {
              "answer": "2",
              "correct": false,
              "score": 1,
              "answer_time": 11.035289287567139
            }
          }
        }
      ],
      "current_round": 2,
      "round_active": false,
      "current_answers": {
        "1": "1",
        "2": "2"
      },
      "answer_times": {
        "1": 7.9486329555511475,
        "2": 11.035289287567139
      },
      "correct_answer": "1",
      "start_time": 1759978883.2221704
    },
    "3888b1ed-a940-4e66-8909-442602da4059": {
      "id": "3888b1ed-a940-4e66-8909-442602da4059",
      "name": "",
      "class_id": "6016fecd-ce97-4856-b957-4cae109416c5",
      "is_active": true,
      "created_date": "2025-10-08",
      "students": {
        "1": {
          "name": "1",
          "score": 4,
          "total_rounds": 2,
          "correct_rounds": 2,
          "last_answer_time": 8.253597497940063,
          "expression": "smile",
          "animation": "celebration",
          "avatar_color": "linear-gradient(135deg, #6b8253 0%, #6febb5 100%)",
          "answers": [],
          "last_answer": "1"
        },
        "2": {
          "name": "2",
          "score": 0,
          "total_rounds": 1,
          "correct_rounds": 0,
          "last_answer_time": 4.767838716506958,
          "expression": "embarrassed",
          "animation": "none",
          "avatar_color": "linear-gradient(135deg, #b76fcd 0%, #2d7891 100%)",
          "answers": [],
          "last_answer": ""
        }
      },
      "submissions": [],
      "round_results": [
        {
          "round": 1,
          "correct_answer": "1",
          "question_score": 1,
          "results": {
            "1": {
              "answer": "1",
              "correct": true,
              "score": 1,
              "answer_time": 2.18798565864563
            },
            "2": {
              "answer": "2",
              "correct": false,
              "score": 0,
              "answer_time": 4.767838716506958
            }
          }
        },
        {
          "round": 2,
          "correct_answer": "1",
          "question_score": 3,
          "results": {
            "1": {
              "answer": "1",
              "correct": true,
              "score": 4,
              "answer_time": 8.253597497940063
            },
            "2": {
              "answer": "",
              "correct": false,
              "score": 0,
              "answer_time": 0
            }
          }
        }
      ],
      "current_round": 2,
      "round_active": false,
      "current_answers": {
        "1": "1"
      },
      "answer_times": {
        "1": 8.253597497940063
      },
      "correct_answer": "1",
      "start_time": 1759979258.823292
    },
    "16c8d158-7f18-4666-95bc-9a169ada5b8f": {
      "id": "16c8d158-7f18-4666-95bc-9a169ada5b8f",
      "name": "test class name",
      "class_id": "6016fecd-ce97-4856-b957-4cae109416c5",
      "is_active": true,
      "created_date": "2025-10-08",
      "students": {
        "1": {
          "name": "1",
          "score": 1,
          "total_rounds": 1,
          "correct_rounds": 1,
          "last_answer_time": 3.618243455886841,
          "expression": "smile",
          "animation": "celebration",
          "avatar_color": "linear-gradient(135deg, #6b8253 0%, #6febb5 100%)",
          "answers": [],
          "last_answer": "1"
        },
        "2": {
          "name": "2",
          "score": 1,
          "total_rounds": 1,
          "correct_rounds": 1,
          "last_answer_time": 7.308198690414429,
          "expression": "smile",
          "animation": "celebration",
          "avatar_color": "linear-gradient(135deg, #b76fcd 0%, #2d7891 100%)",
          "answers": [],
          "last_answer": "1"
        }
      },
      "submissions": [],
      "round_results": [
        {
          "round": 1,
          "correct_answer": "1",
          "question_score": 1,
          "results": {
            "1": {
              "answer": "1",
              "correct": true,
              "score": 1,
              "answer_time": 3.618243455886841
            },
            "2": {
              "answer": "1",
              "correct": true,
              "score": 1,
              "answer_time": 7.308198690414429
            }
          }
        }
      ],
      "current_round": 1,
      "round_active": false,
      "current_answers": {
        "1": "1",
        "2": "1"
      },
      "answer_times": {
        "1": 3.618243455886841,
        "2": 7.308198690414429
      },
      "correct_answer": "1",
      "start_time": 1759979634.7786489
    }
  },
  "current_course": "16c8d158-7f18-4666-95bc-9a169ada5b8f",
  "students": {
    "dce90a34-7312-40fd-9c76-532ea9d06e6b": {
      "id": "dce90a34-7312-40fd-9c76-532ea9d06e6b",
      "name": "11",
      "class_id": "368d7e52-8b84-41e9-b5dc-7fad38eced10",
      "created_date": "2025-10-03"
    },
    "a68c8fab-593f-4999-947d-46cc49b8898a": {
      "id": "a68c8fab-593f-4999-947d-46cc49b8898a",
      "name": "12",
      "class_id": "368d7e52-8b84-41e9-b5dc-7fad38eced10",
      "created_date": "2025-10-03"
    },
    "153527b9-34e5-43e0-a816-798398e1f29c": {
      "id": "153527b9-34e5-43e0-a816-798398e1f29c",
      "name": "13",
      "class_id": "368d7e52-8b84-41e9-b5dc-7fad38eced10",
      "created_date": "2025-10-03"
    },
    "d6f7cf32-9c55-4661-9e48-03740b17ec5f": {
      "id": "d6f7cf32-9c55-4661-9e48-03740b17ec5f",
      "name": "1",
      "class_id": "6016fecd-ce97-4856-b957-4cae109416c5",
      "created_date": "2025-10-08",
      "avatar_color": "linear-gradient(135deg, #6b8253 0%, #6febb5 100%)",
      "total_score_all_courses": 0,
      "courses_attended": [],
      "attendance_rate": 100,
      "absence_count": 0,
      "long_term_member": true
    },
    "a4747145-eed3-4bf1-8880-90bcb26d796e": {
      "id": "a4747145-eed3-4bf1-8880-90bcb26d796e",
      "name": "2",
      "class_id": "6016fecd-ce97-4856-b957-4cae109416c5",
      "created_date": "2025-10-08",
      "avatar_color": "linear-gradient(135deg, #b76fcd 0%, #2d7891 100%)",
      "total_score_all_courses": 0,
      "courses_attended": [],
      "attendance_rate": 100,
      "absence_count": 0,
      "long_term_member": true
    }
  }
}